scheduguru/__init__.py
scheduguru/main.py
scheduguru-0.0.5.dist-info/METADATA
scheduguru-0.0.5.dist-info/WHEEL
scheduguru-0.0.5.dist-info/top_level.txt
scheduguru-0.0.5.dist-info/RECORD
